{
    "name": "k4lt-ost",
    "title": "Original Soundtrack for KULT: Divinity Lost (4th Edition)",
    "description": "",
    "version": "1.0.0",
    "license": "LICENSE",
  "compatibility": {
    "minimum": "10",
    "verified": "10.291",
    "maximum": "11"
  },
  "authors": [
    {
      "name": "YanK",
      "url": "https://fr.tipeee.com/yank",
      "email": "yanklinnomme@gmail.com",
      "discord": "YanK#8683"
    }
  ],
    "dependencies":
	[
		{
		"name": "k4lt",
		"type": "system"
		}
	],
    "packs": [
    {
      "name": "k4lt-ost",
      "label": "Kult Divinity Lost OST",
      "system": "k4lt",
      "module": "k4lt-ost",
      "path": "packs/k4lt-ost.db",
      "entity": "Playlist"
    }
    ],
	"system": ["k4lt"],
    "url": "https://github.com/YanKlInnomme/FoundryVTT-k4lt-ost",
    "manifest": "",
    "download": ""
}
